meiki/AnimeNote.py
meiki/BaseNote.py
meiki/NoteType.py
meiki/core.py
meiki-0.1.0.dist-info/LICENSE
meiki-0.1.0.dist-info/METADATA
meiki-0.1.0.dist-info/WHEEL
meiki-0.1.0.dist-info/top_level.txt
meiki-0.1.0.dist-info/RECORD
