Metadata-Version: 2.1
Name: meiki
Version: 0.1.0
Summary: Meiki Note Taking Library
Author-email: nischkar <mail@nischkar.com>
License: Copyright © 2023 Meiki
Project-URL: Homepage, https://meiki.nischkar.com
Keywords: meiki
Classifier: License :: OSI Approved :: MIT License
Classifier: Programming Language :: Python
Classifier: Programming Language :: Python :: 3
Requires-Python: >=3.4
License-File: LICENSE
Provides-Extra: dev
Requires-Dist: black ; extra == 'dev'
Requires-Dist: pytest ; extra == 'dev'
